[
  {
    "id": "57347c93245977448d35f6e3",
    "name": "Toothpaste",
    "types": [
      "barter"
    ]
  },
  {
    "id": "577e1c9d2459773cd707c525",
    "name": "Printer paper",
    "types": [
      "barter"
    ]
  },
  {
    "id": "59e358a886f7741776641ac3",
    "name": "Clin window cleaner",
    "types": [
      "barter"
    ]
  },
  {
    "id": "5bc9b9ecd4351e3bac122519",
    "name": "Deadlyslob's beard oil",
    "types": [
      "barter"
    ]
  },
  {
    "id": "5e2aef7986f7746d3f3c33f5",
    "name": "Repellent",
    "types": [
      "barter"
    ]
  },
  {
    "id": "5e2af02c86f7746d420957d4",
    "name": "Pack of chlorine",
    "types": [
      "barter"
    ]
  },
  {
    "id": "60b0f561c4449e4cb624c1d7",
    "name": "LVNDMARK's rat poison",
    "types": [
      "barter"
    ]
  },
  {
    "id": "67586c61a0c49554ed0bb4a8",
    "name": "SHYSHKA Christmas tree life extender",
    "types": [
      "barter"
    ]
  }
]